{
	"normal": {
		"bidirectional": [
			[
				"kvthappavko2coeu",
				"mx19tvgt8bqtnjpz"
			],
			[
				"kvthappavko2coeu",
				"2kqygy3kszdq0vyj"
			],
			[
				"2kqygy3kszdq0vyj",
				"rjtn8vayhhdlded0"
			],
			[
				"mx19tvgt8bqtnjpz",
				"580qipg24z65ikgs"
			],
			[
				"uiow69n2ll83ba7c",
				"mdxrtnoe3cpqk2up"
			],
			[
				"uiow69n2ll83ba7c",
				"nn9agiepdbhmakb6"
			],
			[
				"nn9agiepdbhmakb6",
				"iwa4ljmz5unkcjlp"
			],
			[
				"iwa4ljmz5unkcjlp",
				"npfsnq81nlafkmi1"
			],
			[
				"w55dk0n5bia01eme",
				"i4sou5n3qom4pes5"
			],
			[
				"w55dk0n5bia01eme",
				"kycrjv5fokv2i5oq"
			],
			[
				"kzj431vrpy8f109q",
				"2tfjkx7b6mgn0xgc"
			],
			[
				"x8lon5l3n5isxeyt",
				"2tfjkx7b6mgn0xgc"
			],
			[
				"2tfjkx7b6mgn0xgc",
				"1m1qfxf0b07szndo"
			],
			[
				"2tfjkx7b6mgn0xgc",
				"v48avz5dco5h07d2"
			],
			[
				"2tfjkx7b6mgn0xgc",
				"fydv3bmckk7r6odn"
			],
			[
				"fydv3bmckk7r6odn",
				"1m1qfxf0b07szndo"
			],
			[
				"1m1qfxf0b07szndo",
				"x8lon5l3n5isxeyt"
			],
			[
				"x8lon5l3n5isxeyt",
				"v48avz5dco5h07d2"
			],
			[
				"v48avz5dco5h07d2",
				"fydv3bmckk7r6odn"
			],
			[
				"fydv3bmckk7r6odn",
				"yl0wtsb5m85wmvfa"
			],
			[
				"yl0wtsb5m85wmvfa",
				"o19cwf5z60uquym3"
			],
			[
				"o19cwf5z60uquym3",
				"5hcgvn67iorhfl3f"
			],
			[
				"5hcgvn67iorhfl3f",
				"91ejp3f9bph54rm8"
			],
			[
				"yl0wtsb5m85wmvfa",
				"bggfi92ktcmolgzr"
			],
			[
				"bggfi92ktcmolgzr",
				"cbuv1mpusy9uli4f"
			],
			[
				"cbuv1mpusy9uli4f",
				"phljx6dz895twdfc"
			],
			[
				"cbuv1mpusy9uli4f",
				"if5lfydm9eufrfiq"
			],
			[
				"5hcgvn67iorhfl3f",
				"8jx86oimb8xzvf1q"
			],
			[
				"91ejp3f9bph54rm8",
				"i6hw1qpsdgwqagfw"
			],
			[
				"i6hw1qpsdgwqagfw",
				"15j25eluqgelef4l"
			],
			[
				"i6hw1qpsdgwqagfw",
				"1m9kivl8s5f2ukga"
			],
			[
				"1m9kivl8s5f2ukga",
				"4u2o4yvz9f02am6a"
			],
			[
				"1m9kivl8s5f2ukga",
				"3c969v5892itlzd3"
			],
			[
				"3c969v5892itlzd3",
				"kf1ehshxw5zi5guz"
			],
			[
				"phljx6dz895twdfc",
				"vi1qedts6lhjm5ey"
			],
			[
				"vi1qedts6lhjm5ey",
				"1iklyeiz6ifl94ml"
			],
			[
				"vi1qedts6lhjm5ey",
				"29iup0t25e2qpn3d"
			],
			[
				"29iup0t25e2qpn3d",
				"rxoejckexzflc3mj"
			],
			[
				"29iup0t25e2qpn3d",
				"li4d0i1iljuu9weu"
			],
			[
				"li4d0i1iljuu9weu",
				"dzvnm4h7fscahfi1"
			],
			[
				"1m9kivl8s5f2ukga",
				"4u0zgdouq2jwmfpa"
			],
			[
				"29iup0t25e2qpn3d",
				"4sxo4m4qx68iv8pp"
			],
			[
				"z7k7o87nafgwmr7x",
				"uiow69n2ll83ba7c"
			],
			[
				"z7k7o87nafgwmr7x",
				"w55dk0n5bia01eme"
			],
			[
				"siajl5xqw446wx7n",
				"i8lggntzzobypihf"
			],
			[
				"kycrjv5fokv2i5oq",
				"siajl5xqw446wx7n"
			],
			[
				"i4sou5n3qom4pes5",
				"siajl5xqw446wx7n"
			],
			[
				"e9n5ghhftk2k25k7",
				"c4zavsxmlp4sd4jy"
			],
			[
				"7vq12aqwzi3m4d1n",
				"66jtanxorxxif1zs"
			],
			[
				"e9n5ghhftk2k25k7",
				"u6mihkq4mevhnr9v"
			],
			[
				"7vq12aqwzi3m4d1n",
				"u6mihkq4mevhnr9v"
			],
			[
				"c4zavsxmlp4sd4jy",
				"u71z1msna0rledf1"
			],
			[
				"66jtanxorxxif1zs",
				"he5o9rg2sj0rtzrd"
			],
			[
				"u71z1msna0rledf1",
				"98ortdbslmjai2vc"
			],
			[
				"98ortdbslmjai2vc",
				"zsx0kwbv355vezqm"
			],
			[
				"98ortdbslmjai2vc",
				"24z3bwf46pkkx4cb"
			],
			[
				"24z3bwf46pkkx4cb",
				"28ybdwkodfm61q9j"
			],
			[
				"24z3bwf46pkkx4cb",
				"47bkzw5ysyto97rz"
			],
			[
				"47bkzw5ysyto97rz",
				"211h5yy5f5aob8n5"
			],
			[
				"8xauglyl5mqqzwdv",
				"u9wtbnr24n24c6m1"
			],
			[
				"srrwtsfhvo0ynlan",
				"ef6uyw5wwk5o4vy4"
			],
			[
				"8xauglyl5mqqzwdv",
				"srrwtsfhvo0ynlan"
			],
			[
				"srrwtsfhvo0ynlan",
				"tuu7z5qwjjgw0xed"
			],
			[
				"tuu7z5qwjjgw0xed",
				"lhaaeti7hrwz8p5t"
			],
			[
				"he5o9rg2sj0rtzrd",
				"tuu7z5qwjjgw0xed"
			],
			[
				"kzj431vrpy8f109q",
				"u6mihkq4mevhnr9v"
			],
			[
				"51ke7nr6dxe681gu",
				"qm1qbh0mxhxfsx9z"
			],
			[
				"qm1qbh0mxhxfsx9z",
				"uzlj5kiyt34s4dv8"
			],
			[
				"uzlj5kiyt34s4dv8",
				"2tes1y5pnasmitqj"
			],
			[
				"1m1qfxf0b07szndo",
				"51ke7nr6dxe681gu"
			],
			[
				"1m1qfxf0b07szndo",
				"lbs7b5i99gvlj0ei"
			],
			[
				"lbs7b5i99gvlj0ei",
				"37xa5y1dzt2ex450"
			],
			[
				"mce48i6z5g2im5jh",
				"5qxbhy0pm2q5tc51"
			],
			[
				"5qxbhy0pm2q5tc51",
				"phys1a66ir514fo8"
			],
			[
				"phys1a66ir514fo8",
				"haybltii0txrrnzg"
			],
			[
				"v48avz5dco5h07d2",
				"5wmbcqejlwtc0rxa"
			],
			[
				"v48avz5dco5h07d2",
				"mce48i6z5g2im5jh"
			],
			[
				"5wmbcqejlwtc0rxa",
				"3gihrv3fn106udrt"
			],
			[
				"3gihrv3fn106udrt",
				"1240yby2ry4k5oqh"
			],
			[
				"1240yby2ry4k5oqh",
				"yhb8bnfhxmlzgmsl"
			],
			[
				"37xa5y1dzt2ex450",
				"wszvtgqyp7fvxajy"
			],
			[
				"wszvtgqyp7fvxajy",
				"pa46a3em6kgr0dlw"
			]
		],
		"unidirectional": [
			[
				"91ejp3f9bph54rm8",
				"5fceh8hp52p1xqox"
			],
			[
				"phljx6dz895twdfc",
				"5fceh8hp52p1xqox"
			],
			[
				"4u0zgdouq2jwmfpa",
				"z7k7o87nafgwmr7x"
			],
			[
				"4sxo4m4qx68iv8pp",
				"z7k7o87nafgwmr7x"
			],
			[
				"u71z1msna0rledf1",
				"0412j73bt64hfmd3"
			],
			[
				"he5o9rg2sj0rtzrd",
				"0412j73bt64hfmd3"
			],
			[
				"47bkzw5ysyto97rz",
				"kvthappavko2coeu"
			],
			[
				"8xauglyl5mqqzwdv",
				"kvthappavko2coeu"
			]
		]
	},
	"exclusive": {
		"bidirectional": [
			[
				"uiow69n2ll83ba7c",
				"w55dk0n5bia01eme"
			],
			[
				"mdxrtnoe3cpqk2up",
				"nn9agiepdbhmakb6"
			],
			[
				"i4sou5n3qom4pes5",
				"kycrjv5fokv2i5oq"
			],
			[
				"5wmbcqejlwtc0rxa",
				"mce48i6z5g2im5jh"
			],
			[
				"51ke7nr6dxe681gu",
				"lbs7b5i99gvlj0ei"
			]
		]
	}
}