{
  "Restriction Data": {
    "stage": "stage_gunner_expert",
    "itemList": [
      {
        "item": "bypowderandsteel:infernal_enforcerhelmet"
      },
      {
        "item": "bypowderandsteel:infernal_enforcerleggings"
      },
      {
        "item": "bypowderandsteel:infernal_enforcerchestplate"
      },
      {
        "item": "bypowderandsteel:infernal_enforcerboots"
      }
    ],
    "modList": [],
    "tagList": [],
    "exceptionList": [],
    "containerList": ["net.minecraft.inventory.container.WorkbenchContainer"],
    "dimensionList": []
  },
  "Settings": {
    "advancedTooltips": "ALWAYS",
    "itemTitle": "Unavailable Item (Unlock it in the Gunner's skill tree)",
    "pickupDelay": 15,
    "hideInJEI": true,
    "canPickup": true,
    "containerListWhitelist": false,
    "checkPlayerInventory": false,
    "checkPlayerEquipment": true,
    "destroyableBlocks": false,
    "usableItems": false,
    "usableBlocks": false
  }
}
